{
    "@context": "https://schema.org",
    "@type": "Apartment",
    "@id": "https://www.magicbricks.com/propertyDetails/2-BHK-1275-Sq-ft-Multistorey-Apartment-FOR-Sale-Nallagandla-in-Hyderabad&id=4d423639343236353637",
    "url": "https://www.magicbricks.com/propertyDetails/2-BHK-1275-Sq-ft-Multistorey-Apartment-FOR-Sale-Nallagandla-in-Hyderabad&id=4d423639343236353637",
    "numberOfRooms": "2",
    "image": "https://img.staticmb.com/mbphoto/property/cropped_images/2023/Oct/06/Photo_h180_w240/69426567_7_PropertyImage849-1569794671296_180_240.jpg",
    "name": "2 BHK Apartment for Sale in Nalagandla Hyderabad",
    "geo": {
        "@type": "GeoCoordinates",
        "latitude": "17.4633553",
        "longitude": "78.306611"
    },
    "potentialAction": {
        "@type": "BuyAction",
        "seller": {
            "@type": "Person",
            "name": "Srikanth  Bandari"
        }
    },
    "address": {
        "@type": "PostalAddress",
        "addressLocality": "Nallagandla",
        "addressRegion": "Hyderabad",
        "addressCountry": "IN"
    }
}