{
    "@context": "https://schema.org",
    "@type": "SingleFamilyResidence",
    "@id": "https://www.magicbricks.com/propertyDetails/4-BHK-2100-Sq-ft-Residential-House-FOR-Sale-Patancheru-Shankarpalli-Road-in-Hyderabad&id=4d423731323939343531",
    "url": "https://www.magicbricks.com/propertyDetails/4-BHK-2100-Sq-ft-Residential-House-FOR-Sale-Patancheru-Shankarpalli-Road-in-Hyderabad&id=4d423731323939343531",
    "numberOfRooms": "4",
    "image": "https://img.staticmb.com/mbphoto/property/cropped_images/2024/Feb/08/Photo_h180_w240/71299451_3_hatsAppImage20240208at19.02.28df2a9299_180_240.jpg",
    "name": "4 BHK  House for Sale in Patancheru Shankarpalli Road Hyderabad",
    "geo": {
        "@type": "GeoCoordinates",
        "latitude": "17.4980505",
        "longitude": "78.19190982"
    },
    "potentialAction": {
        "@type": "BuyAction",
        "seller": {
            "@type": "Person",
            "name": "DurgaGaneshReddy"
        }
    },
    "address": {
        "@type": "PostalAddress",
        "addressLocality": "Patancheru Shankarpalli Road",
        "addressRegion": "Hyderabad",
        "addressCountry": "IN"
    }
}