{
    "@context": "https://schema.org",
    "@type": "Apartment",
    "@id": "https://www.magicbricks.com/propertyDetails/4-BHK-2000-Sq-ft-Multistorey-Apartment-FOR-Sale-in-Hyderabad&id=4d423737333232353735",
    "url": "https://www.magicbricks.com/propertyDetails/4-BHK-2000-Sq-ft-Multistorey-Apartment-FOR-Sale-in-Hyderabad&id=4d423737333232353735",
    "numberOfRooms": "4",
    "image": "https://img.staticmb.com/mbphoto/property/cropped_images/2025/Jan/25/Photo_h180_w240/77322575_8_1000042038_180_240.jpg",
    "name": "4 BHK Apartment for Sale in Mansarovar heights phase 3 trimulghery secunderabad Hyderabad",
    "potentialAction": {
        "@type": "BuyAction",
        "seller": {
            "@type": "Person",
            "name": "Pankaj Agarwal"
        }
    },
    "address": {
        "@type": "PostalAddress",
        "addressRegion": "Hyderabad",
        "addressCountry": "IN"
    }
}