{
    "@context": "https://schema.org",
    "@type": "Apartment",
    "@id": "https://www.magicbricks.com/propertyDetails/3-BHK-1222-Sq-ft-Multistorey-Apartment-FOR-Sale-Rajendra-Nagar-in-Hyderabad&id=4d423638313935333033",
    "url": "https://www.magicbricks.com/propertyDetails/3-BHK-1222-Sq-ft-Multistorey-Apartment-FOR-Sale-Rajendra-Nagar-in-Hyderabad&id=4d423638313935333033",
    "numberOfRooms": "3",
    "image": "https://img.staticmb.com/mbimages/project/Photo_h310_w462/2019/09/03/Project-Photo-2-The-Pearl-Hyderabad-5126009_600_800_310_462.jpg",
    "name": "3 BHK Apartment for Sale in Rajendranagar Mandal Hyderabad",
    "geo": {
        "@type": "GeoCoordinates",
        "latitude": "17.308096",
        "longitude": "78.39665"
    },
    "potentialAction": {
        "@type": "BuyAction",
        "seller": {
            "@type": "Person",
            "name": "Ramesh"
        }
    },
    "address": {
        "@type": "PostalAddress",
        "addressLocality": "Rajendranagar Mandal",
        "addressRegion": "Hyderabad",
        "addressCountry": "IN"
    }
}